{
  "project_info": {
    "project_number": "482367260628",
    "project_id": "login-2a3ff",
    "storage_bucket": "login-2a3ff.appspot.com"
  },
  "client": [
    {
      "client_info": {
        "mobilesdk_app_id": "1:482367260628:android:295d98f00ee5501c923841",
        "android_client_info": {
          "package_name": "com.example.login"
        }
      },
      "oauth_client": [],
      "api_key": [
        {
          "current_key": "AIzaSyDhG3WSkxdgSYJdQj2J8hnN3av04VM7r08"
        }
      ],
      "services": {
        "appinvite_service": {
          "other_platform_oauth_client": []
        }
      }
    }
  ],
  "configuration_version": "1"
}